[
  { "id": "debt-001", "name": "Afterpay", "balance": 0, "isEstimate": false, "notes": "" },
  { "id": "debt-002", "name": "Neo Credit Card", "balance": 0, "isEstimate": false, "notes": "" },
  {
    "id": "debt-003",
    "name": "Simplii Credit Card",
    "balance": 0,
    "isEstimate": true,
    "notes": "TBD — need to check balance"
  },
  {
    "id": "debt-004",
    "name": "Tangerine LOC",
    "balance": 4111.8,
    "isEstimate": false,
    "notes": "4263.14 - 151.34 payment"
  },
  {
    "id": "debt-005",
    "name": "Tangerine Credit Card",
    "balance": 0,
    "isEstimate": false,
    "notes": ""
  },
  { "id": "debt-006", "name": "Klarna", "balance": 2183.6, "isEstimate": false, "notes": "" },
  { "id": "debt-007", "name": "ICBC", "balance": 2000, "isEstimate": true, "notes": "Estimate" },
  {
    "id": "debt-008",
    "name": "CRA",
    "balance": 4500,
    "isEstimate": true,
    "notes": "Tax debt estimate"
  }
]
